modis_import-0.0.1.dist-info/licenses/LICENSE
src/MODIS_import/MODIS_cli.py
src/MODIS_import/MODIS_download_all.py
src/MODIS_import/MODIS_download_conversion.py
src/MODIS_import/MODIS_full_nc_creation.py
src/MODIS_import/MODIS_nc_creation.py
src/MODIS_import/MODIS_requests.py
src/MODIS_import/__init__.py
src/MODIS_import/__main__.py
modis_import-0.0.1.dist-info/METADATA
modis_import-0.0.1.dist-info/WHEEL
modis_import-0.0.1.dist-info/entry_points.txt
modis_import-0.0.1.dist-info/top_level.txt
modis_import-0.0.1.dist-info/RECORD
