Metadata-Version: 2.4
Name: MODIS_import
Version: 0.0.1
Summary: Import Snow cover NDSI and Land Surface Temperature (LST) from MODIS and produces a netCDF file from configuration files
Author-email: Victor Pozsgay <victor.pozsgay@carleton.ca>
License: GNU GENERAL PUBLIC LICENSE
Project-URL: Homepage, https://github.com/VictorPozsgay/MODIS_import
Classifier: Programming Language :: Python :: 3
Classifier: License :: OSI Approved :: GNU General Public License v3 (GPLv3)
Classifier: Operating System :: POSIX :: Linux
Classifier: Topic :: Scientific/Engineering :: GIS
Classifier: Topic :: Scientific/Engineering :: Atmospheric Science
Requires-Python: >=3.7
License-File: LICENSE
Dynamic: license-file
